gdownlite/__init__.py
gdownlite/__main__.py
gdownlite/downloader.py
gdownlite-0.1.2.dist-info/LICENSE
gdownlite-0.1.2.dist-info/METADATA
gdownlite-0.1.2.dist-info/WHEEL
gdownlite-0.1.2.dist-info/entry_points.txt
gdownlite-0.1.2.dist-info/top_level.txt
gdownlite-0.1.2.dist-info/RECORD
