Metadata-Version: 2.1
Name: gdownlite
Version: 0.1.2
Summary: Simple Google Drive downloader with original filename
Home-page: https://github.com/ceejay06s/gdownlite
Author: Christian Balais
Author-email: christianbalais06@gmail.com
Classifier: Programming Language :: Python :: 3
Classifier: License :: OSI Approved :: MIT License
Requires-Python: >=3.6
License-File: LICENSE
Requires-Dist: requests
